napari_roxas_ai/__init__.py
napari_roxas_ai/napari.yaml
napari_roxas_ai/_assets_files/__init__.py
napari_roxas_ai/_assets_files/_assets_dowloader.py
napari_roxas_ai/_conversion/__init__.py
napari_roxas_ai/_conversion/_cells_vectorization_widget.py
napari_roxas_ai/_crossdating/__init__.py
napari_roxas_ai/_crossdating/_cross_dating_plotter.py
napari_roxas_ai/_edition/__init__.py
napari_roxas_ai/_edition/_cells_layer_editor.py
napari_roxas_ai/_edition/_rings_layer_editor.py
napari_roxas_ai/_edition/_sample_metadata_update.py
napari_roxas_ai/_loading/__init__.py
napari_roxas_ai/_loading/_samples_loading_widget.py
napari_roxas_ai/_measurements/__init__.py
napari_roxas_ai/_measurements/_batch_sample_measurements.py
napari_roxas_ai/_measurements/_sample_measurer.py
napari_roxas_ai/_measurements/_single_sample_measurements.py
napari_roxas_ai/_preparation/__init__.py
napari_roxas_ai/_preparation/_crossdating_handler.py
napari_roxas_ai/_preparation/_metadata_dialog.py
napari_roxas_ai/_preparation/_preparation_widget.py
napari_roxas_ai/_preparation/_worker.py
napari_roxas_ai/_project_directory/__init__.py
napari_roxas_ai/_project_directory/_project_directory_dialog.py
napari_roxas_ai/_reader/__init__.py
napari_roxas_ai/_reader/_crossdating_reader.py
napari_roxas_ai/_reader/_reader.py
napari_roxas_ai/_sample_data/__init__.py
napari_roxas_ai/_sample_data/_data_loader.py
napari_roxas_ai/_saving/__init__.py
napari_roxas_ai/_saving/_samples_saving_widget.py
napari_roxas_ai/_segmentation/__init__.py
napari_roxas_ai/_segmentation/_batch_sample_segmentation.py
napari_roxas_ai/_segmentation/_cells_model.py
napari_roxas_ai/_segmentation/_single_sample_segmentation.py
napari_roxas_ai/_settings/__init__.py
napari_roxas_ai/_settings/_settings_manager.py
napari_roxas_ai/_tests/__init__.py
napari_roxas_ai/_tests/test_cells_model.py
napari_roxas_ai/_tests/test_cells_vectorization_widget.py
napari_roxas_ai/_tests/test_crossdating_reader.py
napari_roxas_ai/_tests/test_preparation.py
napari_roxas_ai-0.1.2.dist-info/licenses/LICENSE
napari_roxas_ai-0.1.2.dist-info/METADATA
napari_roxas_ai-0.1.2.dist-info/WHEEL
napari_roxas_ai-0.1.2.dist-info/entry_points.txt
napari_roxas_ai-0.1.2.dist-info/top_level.txt
napari_roxas_ai-0.1.2.dist-info/RECORD
