Metadata-Version: 2.4
Name: napari-roxas-ai
Version: 0.1.2
Summary: A plugin that integrates the ROXAS AI analysis methods for quantitative wood anatomy in the napari platform
Author: Nicola Antonio Santacroce, Marc Katzenmaier, Triyan Bhardwaj, Georg von Arx
Author-email: The WSL Dendrosciences Group <roxas@wsl.ch>
License: 
Project-URL: Bug Tracker, https://github.com/roxas-ai/napari-roxas-ai/issues
Project-URL: Documentation, https://github.com/roxas-ai/napari-roxas-ai#README.md
Project-URL: Source Code, https://github.com/roxas-ai/napari-roxas-ai
Project-URL: User Support, https://github.com/roxas-ai/napari-roxas-ai/issues
Classifier: Development Status :: 2 - Pre-Alpha
Classifier: Framework :: napari
Classifier: Intended Audience :: Developers
Classifier: License :: OSI Approved :: GNU General Public License v3 (GPLv3)
Classifier: Operating System :: OS Independent
Classifier: Programming Language :: Python
Classifier: Programming Language :: Python :: 3
Classifier: Programming Language :: Python :: 3 :: Only
Classifier: Programming Language :: Python :: 3.9
Classifier: Programming Language :: Python :: 3.10
Classifier: Programming Language :: Python :: 3.11
Classifier: Programming Language :: Python :: 3.12
Classifier: Topic :: Scientific/Engineering :: Image Processing
Requires-Python: >=3.9
License-File: LICENSE
Requires-Dist: magicgui==0.10.0
Requires-Dist: napari[all]==0.5.6
Requires-Dist: numpy<=2.1.3,>=2.0.2
Requires-Dist: opencv-contrib-python-headless==4.11.0.86
Requires-Dist: qtpy==2.4.3
Requires-Dist: rasterio==1.4.3
Requires-Dist: scikit-image<=0.25.2,>=0.24.0
Requires-Dist: matplotlib<=3.10.1,>=3.9.4
Requires-Dist: torch<2.7.0,>=2.2.0; sys_platform == "linux" and platform_machine == "x86_64"
Requires-Dist: torchvision==0.21.0; sys_platform == "linux" and platform_machine == "x86_64"
Requires-Dist: torch<2.7.0,>=2.2.0; sys_platform == "win32" and platform_machine == "AMD64"
Requires-Dist: torchvision==0.21.0; sys_platform == "win32" and platform_machine == "AMD64"
Requires-Dist: torch<2.7.0,>=2.4.0; sys_platform == "darwin" or platform_machine == "arm64"
Requires-Dist: torchvision==0.21.0; sys_platform == "darwin" or platform_machine == "arm64"
Requires-Dist: pytorch-lightning==2.5.1
Requires-Dist: segmentation-models-pytorch==0.4.0
Requires-Dist: albumentations==2.0.5
Requires-Dist: hydra-core==1.3.2
Provides-Extra: testing
Requires-Dist: tox==4.25.0; extra == "testing"
Requires-Dist: pytest==8.3.5; extra == "testing"
Requires-Dist: pytest-cov==6.0.0; extra == "testing"
Requires-Dist: pytest-qt==4.4.0; extra == "testing"
Requires-Dist: napari==0.5.6; extra == "testing"
Requires-Dist: pyqt5==5.15.11; extra == "testing"
Dynamic: license-file
